engineDuplicate.py
python_pptx_duplication_slide-0.0.1.dist-info/LICENSE
python_pptx_duplication_slide-0.0.1.dist-info/METADATA
python_pptx_duplication_slide-0.0.1.dist-info/WHEEL
python_pptx_duplication_slide-0.0.1.dist-info/top_level.txt
python_pptx_duplication_slide-0.0.1.dist-info/RECORD
