Metadata-Version: 2.1
Name: python-pptx-duplication-slide
Version: 0.0.1
Summary: A small example package for duplicating slide in .pptx file
Author-email: Dhevan Abi <yadhevan@gmail.com>
Classifier: Programming Language :: Python :: 3
Classifier: License :: OSI Approved :: MIT License
Classifier: Operating System :: OS Independent
Requires-Python: >=3.10
License-File: LICENSE
